saturn_sync/__init__.py
saturn_sync/plugin/__init__.py
saturn_sync/plugin/grpc_controller_pb2.py
saturn_sync/plugin/grpc_controller_pb2.pyi
saturn_sync/plugin/grpc_controller_pb2_grpc.py
saturn_sync/protocol/__init__.py
saturn_sync/protocol/v1/__init__.py
saturn_sync/protocol/v1/saturnsync_pb2.py
saturn_sync/protocol/v1/saturnsync_pb2.pyi
saturn_sync/protocol/v1/saturnsync_pb2_grpc.py
saturn_sync/sdk.py
saturn_sync-0.2.0.dist-info/LICENSE
saturn_sync-0.2.0.dist-info/METADATA
saturn_sync-0.2.0.dist-info/WHEEL
saturn_sync-0.2.0.dist-info/RECORD
